{
  "id": "skilltree:new_skill_372",
  "bonuses": [
    {
      "type": "skilltree:attribute",
      "attribute": "minecraft:generic.attack_speed",
      "id": "40b645df-317b-4d4b-9c0b-ac91b76e3817",
      "name": "Skill",
      "amount": 0.03,
      "operation": 1,
      "player_multiplier": {
        "item_condition": {
          "equipment_type": "melee_weapon",
          "type": "skilltree:equipment_type"
        },
        "type": "skilltree:gems_amount"
      },
      "player_condition": {
        "type": "skilltree:none"
      }
    }
  ],
  "directConnections": [
    "skilltree:new_skill_371"
  ],
  "longConnections": [],
  "oneWayConnections": [],
  "backgroundTexture": "skilltree:textures/icons/background/notable.png",
  "iconTexture": "skilltree:textures/icons/void.png",
  "borderTexture": "skilltree:textures/tooltip/lesser.png",
  "positionX": -186.06908,
  "positionY": -78.40148,
  "buttonSize": 20,
  "isStartingPoint": false
}