{
  "id": "skilltree:new_skill_202",
  "bonuses": [
    {
      "type": "skilltree:attribute",
      "attribute": "minecraft:generic.max_health",
      "id": "083b3472-08a5-4e45-879f-de58579d5524",
      "name": "Skill",
      "amount": 2.0,
      "operation": 0,
      "player_multiplier": {
        "type": "skilltree:none"
      },
      "player_condition": {
        "type": "skilltree:none"
      }
    },
    {
      "type": "skilltree:attribute",
      "attribute": "skilltree:stealth",
      "id": "94fa21f4-37dc-4b6d-b6d8-1cebfdd656df",
      "name": "Skill",
      "amount": 2.0,
      "operation": 0,
      "player_multiplier": {
        "type": "skilltree:none"
      },
      "player_condition": {
        "type": "skilltree:none"
      }
    }
  ],
  "directConnections": [
    "skilltree:new_skill_201",
    "skilltree:new_skill_153",
    "skilltree:new_skill_216"
  ],
  "longConnections": [],
  "oneWayConnections": [],
  "backgroundTexture": "skilltree:textures/icons/background/lesser.png",
  "iconTexture": "skilltree:textures/icons/void.png",
  "borderTexture": "skilltree:textures/tooltip/lesser.png",
  "title": "Desaparecer en la Multitud",
  "positionX": 198.57051,
  "positionY": 5.6434364,
  "buttonSize": 16,
  "isStartingPoint": false
}