{
  "id": "skilltree:new_skill_197",
  "bonuses": [
    {
      "type": "skilltree:attribute",
      "attribute": "minecraft:generic.max_health",
      "id": "b14b6f2d-29c7-4ff0-8882-94aa8ba7479d",
      "name": "Skill",
      "amount": 2.0,
      "operation": 0,
      "player_multiplier": {
        "type": "skilltree:none"
      },
      "player_condition": {
        "type": "skilltree:none"
      }
    },
    {
      "type": "skilltree:attribute",
      "attribute": "irons_spellbooks:mana_regen",
      "id": "0a9cd7c3-3fb1-447d-b318-4ac47b536e54",
      "name": "Skill",
      "amount": 1.0,
      "operation": 0,
      "player_multiplier": {
        "type": "skilltree:none"
      },
      "player_condition": {
        "type": "skilltree:none"
      }
    }
  ],
  "directConnections": [
    "skilltree:new_skill_145"
  ],
  "longConnections": [],
  "oneWayConnections": [],
  "backgroundTexture": "skilltree:textures/icons/background/lesser.png",
  "iconTexture": "skilltree:textures/icons/void.png",
  "borderTexture": "skilltree:textures/tooltip/lesser.png",
  "title": "Sangre Arcana",
  "positionX": 79.02138,
  "positionY": 212.70667,
  "buttonSize": 16,
  "isStartingPoint": false
}